naver_net/__init__.py
naver_net/main.py
naver_net/bus/__init__.py
naver_net/bus/busclient.py
naver_net/dns/__init__.py
naver_net/dns/dnsserver.py
naver_net/host/__init__.py
naver_net/host/hostname.py
naver_net/mail/__init__.py
naver_net/proxy/__init__.py
naver_net/proxy/proxyclient.py
naver_net/proxy/proxyserver.py
naver_net/vpn/__init__.py
naver_net/vpn/client.py
naver_net/vpn/generate_fernet_key.py
naver_net/vpn/hub.py
naver_net/vpn/protocol.py
naver_net-0.0.2.post2.dist-info/METADATA
naver_net-0.0.2.post2.dist-info/WHEEL
naver_net-0.0.2.post2.dist-info/top_level.txt
naver_net-0.0.2.post2.dist-info/RECORD
