Metadata-Version: 2.1
Name: naver-net
Version: 0.0.2.post2
Summary: A Net Persistence Ancestor Library
Home-page: https://github.com/jacr6/naver-net
Author: Jose Cuevas
Author-email: jose.cuevas.cv@gmail.com
Classifier: Programming Language :: Python :: 3
Classifier: License :: OSI Approved :: MIT License
Classifier: Operating System :: OS Independent
Requires-Dist: naver-config
